{
  "type": "chest",
  "pools": [
    {
      "bonus_rolls": 0.0,
      "entries": [
        {
          "type": "minecraft:item",
          "name": "minecraft:brick",
          "functions": [
            {
              "function": "minecraft:set_components",
              "components": {
                "minecraft:item_name": "steadfast_glyphsherd",
                "minecraft:item_model": "odyssey:steadfast_glyphsherd"
              },
              "conditions": []
            },
            {
              "function": "minecraft:set_name",
              "entity": "this",
              "name": {
                "text": "Steadfast Glyphsherd",
                "bold": false,
                "italic": false
              }
            },
            {
              "function": "minecraft:set_attributes",
              "modifiers": [
                {
                  "attribute": "minecraft:knockback_resistance",
                  "operation": "add_value",
                  "amount": 0.2,
                  "id": "odyssey:glyph.slot",
                  "slot": "armor"
                }
              ]
            }
          ],
          "weight": 1
        }
      ],
      "rolls": 1.0
    }
  ]
}